repo_state/__init__.py
repo_state/enforce_repo_state.py
repo_state/save_repo_state.py
repo_state/state.py
repo_state-0.2.dist-info/DESCRIPTION.rst
repo_state-0.2.dist-info/METADATA
repo_state-0.2.dist-info/RECORD
repo_state-0.2.dist-info/WHEEL
repo_state-0.2.dist-info/entry_points.txt
repo_state-0.2.dist-info/metadata.json
repo_state-0.2.dist-info/top_level.txt
