Metadata-Version: 2.0
Name: repo-state
Version: 0.2
Summary: Capture state of multiple git repositories into a json file, and later enforce that state onto a directory
Home-page: UNKNOWN
Author: Jeff Gable
Author-email: jeff@promenadesoftware.com
License: UNKNOWN
Platform: UNKNOWN
Classifier: Development Status :: 4 - Beta
Classifier: Environment :: Console
Classifier: Intended Audience :: Developers
Classifier: Operating System :: MacOS :: MacOS X
Classifier: Operating System :: POSIX
Classifier: License :: OSI Approved :: MIT License
